Workbook
Name eps_g: Scalars!$B$18
Name etabar: Scalars!$B$16

Sheet Readme
A1: Shanghai waste-to-energy instance
A3: Data of the deterministic model used in the paper “Resilient waste-to-energy network design under uncertainty: A distributionally robust approach”.
A4: What the deterministic model optimises. Daily waste generation is q_mean, the mean of five draws around q_day = q_year/365. Each draw is q_day times Uniform(0.85, 1.45). The recyclable share rho is one draw from Uniform(0.25, 0.35). Both use the GAMS generator with execseed = 20250811, and rho is drawn before the waste samples. q_day is the central observation; q_mean is the number the deterministic model sees.
A5: Money and distance. Distances are generalised kilometres: road kilometres, plus the estuary crossing already converted into road-equivalent kilometres (road circuity 1.30, barge rate 1.50, and 20 km per crossing). The model therefore keeps circ = 1 and does not apply circuity again. Unit transport cost (RMB per tonne) = 20 + 3.0 × distance.
A6: Fixed cost of a plant of class s at site b is the daily class cost times the site premium pi. The same rule, with its own premium, applies to a recovery centre. Premiums run from 1.40 at the most accessible plant site to 0.60 at the remotest, and from 1.35 to 0.65 for recovery centres.
A7: Yellow cells are inputs taken from the code. White cells with formulas are derived from those inputs. Annual fixed costs are divided by 365 inside the workbook.
A8: The support used only as a big-M bound, and not as data of the deterministic objective, is q_lo = 0.75 × q_day and q_up = 1.60 × q_day. A city may use a recovery centre only when the generalised distance is at most 30 km.

Sheet Scalars
A1: Symbol | B1: Value | C1: Unit | D1: Meaning
A2: p_e | B2: 0.65 | C2: RMB/kWh | D2: Electricity price
A3: p_a | B3: 70 | C3: RMB/t | D3: Landfill surcharge
A4: p_d | B4: 140 | C4: RMB/t | D4: Unit cost of direct disposal of residue at a landfill
A5: r | B5: 0.1 | C5: fraction per day | D5: Required rate of return on installed capacity
A6: P | B6: 8 | C6: plants | D6: Maximum number of WTE plants that may be opened
A7: P_r | B7: 5 | C7: centres | D7: Maximum number of recovery centres that may be opened
A8: p_rec | B8: 420 | C8: RMB/t | D8: Selling price of recovered material
A9: delta | B9: 0.15 | C9: fraction | D9: Maximum surge, as a fraction of installed plant capacity
A10: c_ov | B10: 60 | C10: RMB/t | D10: Premium per tonne processed in surge operation
A11: c_res | B11: 20 | C11: RMB/t per day | D11: Reservation price of contracted contingency capacity
A12: c_ex | B12: 220 | C12: RMB/t | D12: Exercise price of contracted contingency capacity
A13: tau | B13: 3 | C13: RMB/t/km | D13: Line-haul rate
... A22: q_up_factor | B22: 1.6 | C22: times q_day | D22: Upper support, used only as a big-M bound
A23: marg_e | B23: =MAX(Plant_classes!E2*$B$2-Plant_classes!D2,Plant_classes!E3*$B$2-Plant_classes!D3,Plant_classes!E4*$B$2-Plant_classes!D4,Plant_classes!E5*$B$2-Plant_classes!D5,Plant_classes!E6*$B$2-Plant_classes!D6) | C23: RMB/t | D23: Largest energy margin of a plant class, e×p_e − v
A24: p_pen | B24: 2697.26 | C24: RMB/t | D24: Last-resort outlet. Equals max{4×max(c2 + p_a + v_L), marg_e, recycling margin, 4×c_ex}. Evaluated in GAMS as 2697.26.
A25: pi_rec | B25: 300.31 | C25: RMB/t | D25: Largest margin on a marketed tonne plus the energy margin. Evaluated in GAMS as 300.31. Used only to keep p_pen above that margin.

Sheet Cities
A1: ID | B1: District | C1: Place | D1: Latitude | E1: Longitude | F1: Landmass | G1: Annual MSW (t/year) | H1: Central generation (t/day) | I1: Recyclable share | J1: Mean generation used by the model (t/day) | K1: Responsiveness kappa (1/RMB) | L1: Saturation budget (RMB/day) | M1: Participation ceiling (t/day)
A2: i1 | B2: Pu Dong | C2: Lujiazui | D2: 31.24 | E2: 121.506 | F2: Shanghai mainland | G2: 74150 | H2: =G2/365 | I2: 0.29497171 | J2: 244.6629 | K2: 0.00022 | L2: =-LN(eps_g)/K2 | M2: =etabar*I2*J2
A3: i2 | B3: Pu Dong | C3: Century Park | D3: 31.22 | E3: 121.554 | F3: Shanghai mainland | G3: 77873 | H3: =G3/365 | I3: 0.28559767 | J3: 271.62411 | K3: 0.00026 | L3: =-LN(eps_g)/K3 | M3: =etabar*I3*J3
A4: i3 | B4: Pu Dong | C4: Zhangjiang | D4: 31.205 | E4: 121.596 | F4: Shanghai mainland | G4: 53984 | H4: =G4/365 | I4: 0.31268246 | J4: 180.92282 | K4: 0.0003 | L4: =-LN(eps_g)/K4 | M4: =etabar*I4*J4
A5: i4 | B5: Pu Dong | C5: Jinqiao | D5: 31.26 | E5: 121.59 | F5: Shanghai mainland | G5: 65618 | H5: =G5/365 | I5: 0.33548442 | J5: 215.91501 | K5: 0.00024 | L5: =-LN(eps_g)/K5 | M5: =etabar*I5*J5
A6: i5 | B6: Pu Dong | C6: Chuansha | D6: 31.19 | E6: 121.69 | F6: Shanghai mainland | G6: 56621 | H6: =G6/365 | I6: 0.25348839 | J6: 185.41006 | K6: 0.00021 | L6: =-LN(eps_g)/K6 | M6: =etabar*I6*J6
A7: i6 | B7: Pu Dong | C7: Huinan / Nanhui | D7: 31.05 | E7: 121.76 | F7: Shanghai mainland | G7: 88421 | H7: =G7/365 | I7: 0.34761676 | J7: 285.15875 | K7: 0.00028 | L7: =-LN(eps_g)/K7 | M7: =etabar*I7*J7
A8: i7 | B8: Huang Pu | D8: 31.22 | E8: 121.49 | F8: Shanghai mainland | G8: 75236 | H8: =G8/365 | I8: 0.33871528 | J8: 225.97536 | K8: 0.00025 | L8: =-LN(eps_g)/K8 | M8: =etabar*I8*J8
A9: i8 | B9: Lu Wan | D9: 31.213 | E9: 121.475 | F9: Shanghai mainland | G9: 73684 | H9: =G9/365 | I9: 0.28477713 | J9: 231.46348 | K9: 0.00023 | L9: =-LN(eps_g)/K9 | M9: =etabar*I9*J9
A10: i9 | B10: Xu Hui | D10: 31.1885 | E10: 121.4368 | F10: Shanghai mainland | G10: 65618 | H10: =G10/365 | I10: 0.30163252 | J10: 220.14296 | K10: 0.00029 | L10: =-LN(eps_g)/K10 | M10: =etabar*I10*J10
A11: i10 | B11: Chang Ning | D11: 31.218 | E11: 121.4245 | F11: Shanghai mainland | G11: 52432 | H11: =G11/365 | I11: 0.28993854 | J11: 164.0618 | K11: 0.00027 | L11: =-LN(eps_g)/K11 | M11: =etabar*I11*J11
A12: i11 | B12: Jing An | D12: 31.229 | E12: 121.448 | F12: Shanghai mainland | G12: 54604 | H12: =G12/365 | I12: 0.2768197 | J12: 179.07322 | K12: 0.00022 | L12: =-LN(eps_g)/K12 | M12: =etabar*I12*J12
A13: i12 | B13: Pu Tuo | C13: Zhenru | D13: 31.26 | E13: 121.4 | F13: Shanghai mainland | G13: 39247 | H13: =G13/365 | I13: 0.29807988 | J13: 124.60722 | K13: 0.00026 | L13: =-LN(eps_g)/K13 | M13: =etabar*I13*J13
A14: i13 | B14: Pu Tuo | C14: Changfeng | D14: 31.235 | E14: 121.39 | F14: Shanghai mainland | G14: 51346 | H14: =G14/365 | I14: 0.30788891 | J14: 170.18302 | K14: 0.0003 | L14: =-LN(eps_g)/K14 | M14: =etabar*I14*J14
A15: i14 | B15: Za Bei | D15: 31.258 | E15: 121.446 | F15: Shanghai mainland | G15: 60964 | H15: =G15/365 | I15: 0.31517765 | J15: 216.27653 | K15: 0.00024 | L15: =-LN(eps_g)/K15 | M15: =etabar*I15*J15
A16: i15 | B16: Hong Kou | D16: 31.2646 | E16: 121.489 | F16: Shanghai mainland | G16: 39712 | H16: =G16/365 | I16: 0.27557711 | J16: 137.11515 | K16: 0.00021 | L16: =-LN(eps_g)/K16 | M16: =etabar*I16*J16
A17: i16 | B17: Yang Pu | D17: 31.2705 | E17: 121.526 | F17: Shanghai mainland | G17: 43900 | H17: =G17/365 | I17: 0.27366177 | J17: 128.51942 | K17: 0.00028 | L17: =-LN(eps_g)/K17 | M17: =etabar*I17*J17
A18: i17 | B18: Min Hang | C18: Xinzhuang | D18: 31.112 | E18: 121.381 | F18: Shanghai mainland | G18: 28078 | H18: =G18/365 | I18: 0.26998042 | J18: 95.800761 | K18: 0.00025 | L18: =-LN(eps_g)/K18 | M18: =etabar*I18*J18
A19: i18 | B19: Min Hang | C19: Qibao | D19: 31.155 | E19: 121.345 | F19: Shanghai mainland | G19: 75236 | H19: =G19/365 | I19: 0.25429048 | J19: 266.86145 | K19: 0.00023 | L19: =-LN(eps_g)/K19 | M19: =etabar*I19*J19
A20: i19 | B20: Min Hang | C20: Meilong | D20: 31.14 | E20: 121.41 | F20: Shanghai mainland | G20: 47623 | H20: =G20/365 | I20: 0.32929474 | J20: 163.49212 | K20: 0.00029 | L20: =-LN(eps_g)/K20 | M20: =etabar*I20*J20
A21: i20 | B21: Min Hang | C21: Wujing | D21: 31.03 | E21: 121.45 | F21: Shanghai mainland | G21: 100680 | H21: =G21/365 | I21: 0.25367165 | J21: 285.27194 | K21: 0.00027 | L21: =-LN(eps_g)/K21 | M21: =etabar*I21*J21
A22: i21 | B22: Bao Shang | C22: Youyi | D22: 31.405 | E22: 121.489 | F22: Shanghai mainland | G22: 100060 | H22: =G22/365 | I22: 0.28251959 | J22: 310.97324 | K22: 0.00022 | L22: =-LN(eps_g)/K22 | M22: =etabar*I22*J22
A23: i22 | B23: Bao Shang | C23: Dachang | D23: 31.31 | E23: 121.42 | F23: Shanghai mainland | G23: 75236 | H23: =G23/365 | I23: 0.33171105 | J23: 263.62104 | K23: 0.00026 | L23: =-LN(eps_g)/K23 | M23: =etabar*I23*J23
A24: i23 | B24: Bao Shang | C24: Luodian | D24: 31.42 | E24: 121.36 | F24: Shanghai mainland | G24: 65618 | H24: =G24/365 | I24: 0.25689465 | J24: 210.33886 | K24: 0.0003 | L24: =-LN(eps_g)/K24 | M24: =etabar*I24*J24
A25: i24 | B25: Jia Ding | C25: Jiading town | D25: 31.375 | E25: 121.25 | F25: Shanghai mainland | G25: 88421 | H25: =G25/365 | I25: 0.26552708 | J25: 279.1186 | K25: 0.00024 | L25: =-LN(eps_g)/K25 | M25: =etabar*I25*J25
A26: i25 | B26: Jia Ding | C26: Anting | D26: 31.295 | E26: 121.16 | F26: Shanghai mainland | G26: 64687 | H26: =G26/365 | I26: 0.28155049 | J26: 186.73195 | K26: 0.00021 | L26: =-LN(eps_g)/K26 | M26: =etabar*I26*J26
A27: i26 | B27: Jia Ding | C27: Nanxiang | D27: 31.295 | E27: 121.31 | F27: Shanghai mainland | G27: 89507 | H27: =G27/365 | I27: 0.28592571 | J27: 286.43252 | K27: 0.00028 | L27: =-LN(eps_g)/K27 | M27: =etabar*I27*J27
A28: i27 | B28: Jing Shan | C28: Zhujing | D28: 30.9 | E28: 121.17 | F28: Shanghai mainland | G28: 92144 | H28: =G28/365 | I28: 0.32281259 | J28: 288.6212 | K28: 0.00025 | L28: =-LN(eps_g)/K28 | M28: =etabar*I28*J28
A29: i28 | B29: Jing Shan | C29: Shihua | D29: 30.725 | E29: 121.34 | F29: Shanghai mainland | G29: 55069 | H29: =G29/365 | I29: 0.34691689 | J29: 178.21024 | K29: 0.00023 | L29: =-LN(eps_g)/K29 | M29: =etabar*I29*J29
... A41: i40 | B41: Chong Ming | C41: Changxing island town | D41: 31.408 | E41: 121.66 | F41: Changxing island | G41: 102690 | H41: =G41/365 | I41: 0.2898948 | J41: 323.73421 | K41: 0.00027 | L41: =-LN(eps_g)/K41 | M41: =etabar*I41*J41

Sheet WTE_plants
A1: ID | B1: Name | C1: Latitude | D1: Longitude | E1: Landmass | F1: Mean haul from the cities (km) | G1: Land premium
A2: b1 | B2: Yuqiao | C2: 31.168 | D2: 121.618 | E2: Shanghai mainland | F2: 39.382688 | G2: 1.3150504
A3: b2 | B3: Laogang | C3: 30.915 | D3: 121.825 | E3: Shanghai mainland | F3: 72.052058 | G3: 0.85345334
A4: b3 | B4: Feng Xian | C4: 30.93 | D4: 121.56 | E4: Shanghai mainland | F4: 51.483742 | G4: 1.1440703
A5: b4 | B5: Song Jiang | C5: 31 | D5: 121.19 | E5: Shanghai mainland | F5: 48.904238 | G5: 1.180517
A6: b5 | B6: Qing Pu | C6: 31.115 | D6: 121.08 | E6: Shanghai mainland | F6: 51.819055 | G6: 1.1393326
A7: b6 | B7: Jiang Qiao | C7: 31.265 | D7: 121.32 | E7: Shanghai mainland | F7: 33.370407 | G7: 1.4
A8: b7 | B8: Luo Jing | C8: 31.42 | D8: 121.42 | E8: Shanghai mainland | F8: 43.269315 | G8: 1.2601349
A9: b8 | B9: Chong Ming | C9: 31.61 | D9: 121.46 | E9: Chongming island | F9: 89.99013 | G9: 0.6
A10: b9 | B10: Jin Shan | C10: 30.85 | D10: 121.26 | E10: Shanghai mainland | F10: 59.976467 | G10: 1.0240736
A11: b10 | B11: Min Hang | C11: 31.055 | D11: 121.43 | E11: Shanghai mainland | F11: 36.549175 | G11: 1.3550861

Sheet Recovery_centres
A1: ID | B1: Name | C1: Latitude | D1: Longitude | E1: Landmass | F1: Mean haul from the cities (km) | G1: Land premium
A2: j1 | B2: Puxi north | C2: 31.25 | D2: 121.41 | E2: Shanghai mainland | F2: 29.816275 | G2: 1.35
A3: j2 | B3: Pudong | C3: 31.22 | D3: 121.59 | E3: Shanghai mainland | F3: 36.472295 | G3: 1.1008011
A4: j3 | B4: South-west | C4: 31.07 | D4: 121.33 | E4: Shanghai mainland | F4: 36.60602 | G4: 1.0957945
A5: j4 | B5: North | C5: 31.34 | D5: 121.36 | E5: Shanghai mainland | F5: 36.40998 | G5: 1.1031341
A6: j5 | B6: South | C6: 30.94 | D6: 121.51 | E6: Shanghai mainland | F6: 48.51304 | G6: 0.65
A7: j6 | B7: West | C7: 31.15 | D7: 121.15 | E7: Shanghai mainland | F7: 44.446737 | G7: 0.80224087

Sheet Landfills
A1: ID | B1: Name | C1: Latitude | D1: Longitude | E1: Landmass | F1: Capacity (t/day) | G1: Unit operating cost (RMB/t)
A2: l1 | B2: Laogang | C2: 30.88 | D2: 121.86 | E2: Shanghai mainland | F2: 350 | G2: 80
A3: l2 | B3: Qing Pu | C3: 31.13 | D3: 121.06 | E3: Shanghai mainland | F3: 600 | G3: 50
A4: l3 | B4: Chong Ming | C4: 31.64 | D4: 121.4 | E4: Chongming island | F4: 450 | G4: 60

Sheet Plant_classes
A1: Class | B1: Capacity (t/day) | C1: Fixed cost (RMB/year) | D1: Operating cost (RMB/t) | E1: Electricity (kWh/t) | F1: Residue share | G1: Fixed cost (RMB/day)
A2: s1 | B2: 700 | C2: 12800000 | D2: 130 | E2: 265 | F2: 0.8 | G2: =C2/365
A3: s2 | B3: 1000 | C3: 17200000 | D3: 123 | E3: 270 | F3: 0.825 | G3: =C3/365
A4: s3 | B4: 1300 | C4: 21400000 | D4: 118 | E4: 274 | F4: 0.85 | G4: =C4/365
A5: s4 | B5: 1600 | C5: 25100000 | D5: 113 | E5: 278 | F5: 0.875 | G5: =C5/365
A6: s5 | B6: 2000 | C6: 29900000 | D6: 110 | E6: 280 | F6: 0.9 | G6: =C6/365

Sheet Recovery_classes
A1: Class | B1: Capacity (t/day) | C1: Fixed cost (RMB/year) | D1: Operating cost (RMB/t) | E1: Marketable share | F1: Fixed cost (RMB/day)
A2: z1 | B2: 400 | C2: 6700000 | D2: 95 | E2: 0.7 | F2: =C2/365
A3: z2 | B3: 600 | C3: 9200000 | D3: 88 | E3: 0.75 | F3: =C3/365
A4: z3 | B4: 800 | C4: 11400000 | D4: 82 | E4: 0.8 | F4: =C4/365

Sheet Plant_fixed_cost
A1: Daily fixed cost (RMB/day) = class cost × site premium
A2: Site | B2: s1 | C2: s2 | D2: s3 | E2: s4 | F2: s5
A3: b1 | B3: =WTE_plants!G2*Plant_classes!G2 | C3: =WTE_plants!G2*Plant_classes!G3 | D3: =WTE_plants!G2*Plant_classes!G4 | E3: =WTE_plants!G2*Plant_classes!G5 | F3: =WTE_plants!G2*Plant_classes!G6
A4: b2 | B4: =WTE_plants!G3*Plant_classes!G2 | C4: =WTE_plants!G3*Plant_classes!G3 | D4: =WTE_plants!G3*Plant_classes!G4 | E4: =WTE_plants!G3*Plant_classes!G5 | F4: =WTE_plants!G3*Plant_classes!G6
A5: b3 | B5: =WTE_plants!G4*Plant_classes!G2 | C5: =WTE_plants!G4*Plant_classes!G3 | D5: =WTE_plants!G4*Plant_classes!G4 | E5: =WTE_plants!G4*Plant_classes!G5 | F5: =WTE_plants!G4*Plant_classes!G6
A6: b4 | B6: =WTE_plants!G5*Plant_classes!G2 | C6: =WTE_plants!G5*Plant_classes!G3 | D6: =WTE_plants!G5*Plant_classes!G4 | E6: =WTE_plants!G5*Plant_classes!G5 | F6: =WTE_plants!G5*Plant_classes!G6
A7: b5 | B7: =WTE_plants!G6*Plant_classes!G2 | C7: =WTE_plants!G6*Plant_classes!G3 | D7: =WTE_plants!G6*Plant_classes!G4 | E7: =WTE_plants!G6*Plant_classes!G5 | F7: =WTE_plants!G6*Plant_classes!G6
A8: b6 | B8: =WTE_plants!G7*Plant_classes!G2 | C8: =WTE_plants!G7*Plant_classes!G3 | D8: =WTE_plants!G7*Plant_classes!G4 | E8: =WTE_plants!G7*Plant_classes!G5 | F8: =WTE_plants!G7*Plant_classes!G6
A9: b7 | B9: =WTE_plants!G8*Plant_classes!G2 | C9: =WTE_plants!G8*Plant_classes!G3 | D9: =WTE_plants!G8*Plant_classes!G4 | E9: =WTE_plants!G8*Plant_classes!G5 | F9: =WTE_plants!G8*Plant_classes!G6
A10: b8 | B10: =WTE_plants!G9*Plant_classes!G2 | C10: =WTE_plants!G9*Plant_classes!G3 | D10: =WTE_plants!G9*Plant_classes!G4 | E10: =WTE_plants!G9*Plant_classes!G5 | F10: =WTE_plants!G9*Plant_classes!G6
A11: b9 | B11: =WTE_plants!G10*Plant_classes!G2 | C11: =WTE_plants!G10*Plant_classes!G3 | D11: =WTE_plants!G10*Plant_classes!G4 | E11: =WTE_plants!G10*Plant_classes!G5 | F11: =WTE_plants!G10*Plant_classes!G6
A12: b10 | B12: =WTE_plants!G11*Plant_classes!G2 | C12: =WTE_plants!G11*Plant_classes!G3 | D12: =WTE_plants!G11*Plant_classes!G4 | E12: =WTE_plants!G11*Plant_classes!G5 | F12: =WTE_plants!G11*Plant_classes!G6

Sheet Recovery_fixed_cost
A1: Daily fixed cost (RMB/day) = class cost × site premium
A2: Site | B2: z1 | C2: z2 | D2: z3
A3: j1 | B3: =Recovery_centres!G2*Recovery_classes!F2 | C3: =Recovery_centres!G2*Recovery_classes!F3 | D3: =Recovery_centres!G2*Recovery_classes!F4
A4: j2 | B4: =Recovery_centres!G3*Recovery_classes!F2 | C4: =Recovery_centres!G3*Recovery_classes!F3 | D4: =Recovery_centres!G3*Recovery_classes!F4
A5: j3 | B5: =Recovery_centres!G4*Recovery_classes!F2 | C5: =Recovery_centres!G4*Recovery_classes!F3 | D5: =Recovery_centres!G4*Recovery_classes!F4
A6: j4 | B6: =Recovery_centres!G5*Recovery_classes!F2 | C6: =Recovery_centres!G5*Recovery_classes!F3 | D6: =Recovery_centres!G5*Recovery_classes!F4
A7: j5 | B7: =Recovery_centres!G6*Recovery_classes!F2 | C7: =Recovery_centres!G6*Recovery_classes!F3 | D7: =Recovery_centres!G6*Recovery_classes!F4
A8: j6 | B8: =Recovery_centres!G7*Recovery_classes!F2 | C8: =Recovery_centres!G7*Recovery_classes!F3 | D8: =Recovery_centres!G7*Recovery_classes!F4

Sheet Dist_city_plant
A1: City to WTE plant, generalised km
A2: From \ to | B2: b1 | C2: b2 | D2: b3 | E2: b4 | F2: b5 | G2: b6 | H2: b7 | I2: b8 | J2: b9 | K2: b10
A3: i1 | B3: 17.3019 | C3: 61.1721 | D3: 45.06 | E3: 52.1584 | F3: 55.7136 | G3: 23.3046 | H3: 27.979 | I3: 84.0287 | J3: 63.7985 | K3: 28.2083
A4: i2 | B4: 10.8924 | C4: 55.2057 | D4: 41.693 | E4: 55.0509 | F4: 60.5888 | G4: 29.6814 | H4: 33.1918 | I4: 89.3553 | J4: 64.4469 | K4: 28.2522
A5: i3 | B5: 5.9754 | C5: 50.4125 | D5: 39.7806 | E5: 58.2623 | F5: 65.175 | G5: 35.2391 | H5: 37.8135 | I5: 93.9542 | J5: 65.8346 | K5: 29.7862
A6: i4 | B6: 13.6714 | C6: 57.4956 | D6: 47.5814 | E6: 62.039 | F6: 66.4869 | G6: 33.4323 | H6: 31.1748 | I6: 87.1483 | J6: 71.7102 | K6: 35.5061
A7: i5 | B7: 9.4576 | C7: 42.9178 | D7: 40.6917 | E7: 67.6551 | F7: 76.2805 | G7: 47.0557 | H7: 47.0135 | I7: 102.8401 | J7: 72.2652 | K7: 37.5841
A8: i6 | B8: 24.428 | C8: 21.0079 | D8: 30.1754 | E8: 70.9281 | F8: 84.6974 | G8: 62.6266 | H8: 67.8258 | I8: 123.898 | J8: 68.2481 | K8: 40.8586
A9: i7 | B9: 17.5203 | C9: 60.3493 | D9: 42.5776 | E9: 48.7786 | F9: 52.9525 | G9: 22.0168 | H9: 30.0269 | I9: 85.8767 | J9: 60.3279 | K9: 24.854
A10: i8 | B10: 18.8474 | C10: 60.9285 | D10: 42.0191 | E10: 46.7145 | F10: 50.8876 | G10: 20.5927 | H10: 30.5245 | I10: 86.1795 | J10: 58.576 | K10: 23.3851
A11: i9 | B11: 22.6243 | C11: 62.0896 | D11: 40.1666 | E11: 40.837 | F11: 45.416 | G11: 18.1657 | H11: 33.3422 | I11: 88.319 | J11: 53.354 | K11: 19.2086
A12: i10 | B12: 25.0093 | C12: 65.994 | D12: 44.6681 | E12: 42.7167 | F12: 45.1443 | G12: 14.5945 | H12: 29.0421 | I12: 83.8588 | J12: 56.683 | K12: 23.4405
A13: i11 | B13: 22.7988 | C13: 64.9264 | D13: 45.1611 | E13: 45.866 | F13: 48.4141 | G13: 16.6693 | H13: 27.6735 | I13: 82.9924 | J13: 59.2427 | K13: 25.1109
A14: i12 | B14: 30.0533 | C14: 72.3015 | D14: 51.4055 | E14: 45.5264 | F14: 44.7631 | G14: 9.9296 | H14: 23.1323 | I14: 77.3927 | J14: 61.4314 | K14: 29.7011
... A42: i40 | B42: 58.319 | C42: 99.8715 | D42: 92.8267 | E42: 103.7719 | F42: 104.6216 | G42: 68.4397 | H42: 54.2687 | I42: 60.5657 | J42: 115.7379 | K42: 79.7934

Sheet Dist_city_landfill
A1: City to landfill, generalised km
A2: From \ to | B2: l1 | C2: l2 | D2: l3
A3: i1 | B3: 67.8115 | C3: 57.432 | D3: 83.3775
A4: i2 | B4: 61.8355 | C4: 62.508 | D4: 88.7042
A5: i3 | B5: 57.0143 | C5: 67.2241 | D5: 93.3031
A6: i4 | B6: 64.0385 | C6: 68.2205 | D6: 86.4972
A7: i5 | B7: 49.2809 | C7: 78.4661 | D7: 102.189
A8: i6 | B8: 27.3936 | C8: 87.416 | D8: 123.2469
A9: i7 | B9: 66.9825 | C9: 54.7813 | D9: 85.2255
A10: i8 | B10: 67.549 | C10: 52.742 | D10: 85.5284
A11: i9 | B11: 68.6385 | C11: 47.3978 | D11: 87.6679
A12: i10 | B12: 72.5754 | C12: 46.8627 | D12: 83.2077
A13: i11 | B13: 71.541 | C13: 50.0962 | D13: 82.3413
A14: i12 | B14: 78.9084 | C14: 46.052 | D14: 76.7416
... A42: i40 | B42: 106.1947 | C42: 105.8047 | D42: 68.9354

Sheet Dist_plant_landfill
A1: WTE plant to landfill, generalised km
A2: From \ to | B2: l1 | C2: l2 | D2: l3
A3: b1 | B3: 51.1016 | C3: 69.2931 | D3: 99.239
A4: b2 | B4: 6.6397 | C4: 99.6183 | D4: 143.7155
A5: b3 | B5: 37.8275 | C5: 68.2481 | D5: 127.4844
A6: b4 | B6: 84.7172 | C6: 24.6617 | D6: 116.6308
A7: b5 | B7: 102.2982 | C7: 3.2832 | D7: 106.8426
A8: b6 | B8: 86.7847 | C8: 37.5841 | D8: 75.9542
A9: b7 | B9: 94.8276 | C9: 61.0237 | D9: 55.5149
A10: b8 | B10: 150.9651 | C10: 107.018 | D10: 8.5888
A11: b9 | B11: 74.4019 | C11: 47.2544 | D11: 136.0686
A12: b10 | B12: 58.8763 | C12: 47.0557 | D12: 106.4394

Sheet Dist_city_recovery
A1: City to recovery centre, generalised km
A2: From \ to | B2: j1 | C2: j2 | D2: j3 | E2: j4 | F2: j5 | G2: j6
A3: i1 | B3: 11.9709 | C3: 10.7889 | D3: 32.7394 | E3: 23.0933 | F3: 43.1267 | G3: 45.9306
A4: i2 | B4: 18.3406 | C4: 4.4566 | D4: 35.1265 | E4: 29.569 | F4: 40.6158 | G4: 51.0152
A5: i3 | B5: 23.9172 | C5: 2.2805 | D5: 38.2221 | E5: 35.0732 | F5: 39.5525 | G5: 55.7756
A6: i4 | B6: 22.3294 | C6: 5.7498 | D6: 42.2127 | E6: 30.7074 | F6: 47.0528 | G6: 56.7183
A7: i5 | B7: 35.7194 | C7: 13.1091 | D7: 47.7879 | E7: 46.1933 | F7: 42.2844 | G7: 67.096
A8: i6 | B8: 51.9985 | C8: 32.2499 | D8: 53.3093 | E8: 64.7285 | F8: 34.754 | G8: 76.8707
A9: i7 | B9: 10.8017 | C9: 12.3795 | D9: 29.2787 | E9: 23.5911 | F9: 40.325 | G9: 43.2763
A10: i8 | B10: 9.6455 | C10: 14.2719 | D10: 27.2901 | E10: 23.1505 | F10: 39.4812 | G10: 41.2399
A11: i9 | B11: 9.4424 | C11: 19.4984 | D11: 21.5629 | E11: 23.7624 | F11: 36.8524 | G11: 35.9331
A12: i10 | B12: 4.9377 | C12: 20.49 | D12: 24.2788 | E12: 19.2693 | F12: 41.3394 | G12: 35.3596
A13: i11 | B13: 5.5894 | C13: 17.6264 | D13: 27.125 | E13: 19.3201 | F13: 42.2457 | G13: 38.5991
A14: i12 | B14: 1.8971 | C14: 24.2136 | D14: 28.6536 | E14: 12.5205 | F14: 47.9721 | G14: 34.754
... A42: i40 | B42: 59.6159 | C42: 50.9817 | D42: 84.6994 | E42: 60.8131 | F42: 92.3258 | G42: 94.6037

Sheet Dist_recovery_plant
A1: Recovery centre to WTE plant, generalised km
A2: From \ to | B2: b1 | C2: b2 | D2: b3 | E2: b4 | F2: b5 | G2: b6 | H2: b7 | I2: b8 | J2: b9 | K2: b10
A3: j1 | B3: 28.319 | C3: 70.415 | D3: 49.6055 | E3: 45.0907 | F3: 45.2271 | G3: 11.3482 | H3: 24.4682 | I3: 79.008 | J3: 60.4226 | K3: 28.1396
A4: j2 | B4: 8.2394 | C4: 52.6166 | D4: 41.8515 | E4: 58.7547 | F4: 64.9144 | G4: 34.0447 | H4: 35.6289 | I4: 91.7556 | J4: 67.0647 | K4: 30.901
A5: j3 | B5: 38.335 | C5: 65.2033 | D5: 34.8668 | E5: 20.0405 | F5: 31.6175 | G5: 28.0578 | H5: 51.5301 | I5: 104.4181 | J5: 32.79 | K5: 12.5658
A6: j4 | B6: 40.3905 | C6: 83.94 | D6: 63.9254 | E6: 53.2122 | F6: 47.4084 | G6: 11.8638 | H6: 13.6899 | I6: 65.5142 | J6: 71.5152 | K6: 41.8741
A7: j5 | B7: 35.3963 | C7: 39.1606 | D7: 6.3545 | E7: 40.5423 | F7: 58.8763 | G7: 52.3045 | H7: 69.8919 | I7: 125.1559 | J7: 33.5439 | K7: 19.2704
A8: j6 | B8: 57.9937 | C8: 90.1312 | D8: 59.8017 | E8: 22.1232 | F8: 10.0202 | G8: 26.7612 | H8: 51.2204 | I8: 98.8914 | J8: 45.2228 | K8: 37.2555

Sheet Dist_recovery_landfill
A1: Recovery centre to landfill, generalised km
A2: From \ to | B2: l1 | C2: l2 | D2: l3
A3: j1 | B3: 77.0201 | C3: 46.6356 | D3: 78.3569
A4: j2 | B4: 59.2101 | C4: 66.8745 | D4: 91.1044
A5: j3 | B5: 71.0687 | C5: 34.5194 | D5: 103.767
A6: j4 | B6: 90.5735 | C6: 47.8592 | D6: 64.8631
A7: j5 | B7: 44.1782 | C7: 62.0425 | D7: 124.5047
A8: j6 | B8: 96.0819 | C8: 11.5065 | D8: 98.2403
